snaketool_utils/__init__.py
snaketool_utils/cli_utils.py
snaketool_utils-0.0.5.dist-info/LICENSE
snaketool_utils-0.0.5.dist-info/METADATA
snaketool_utils-0.0.5.dist-info/WHEEL
snaketool_utils-0.0.5.dist-info/top_level.txt
snaketool_utils-0.0.5.dist-info/RECORD
