Metadata-Version: 2.1
Name: snaketool_utils
Version: 0.0.5
Summary: Utility functions for Snaketool CLI
Home-page: https://github.com/beardymcjohnface/snaketool-utils
Author: Michael Roach
Author-email: beardymcjohnface@gmail.com
Requires-Python: >=3.9
License-File: LICENSE
Requires-Dist: pyyaml >=6.0
Requires-Dist: click >=8.1.3
